{
  "parent": "dragonsurvival:good/collect_good_key",
  "display": {
    "icon": {
      "id": "dragonsurvival:good_dragon_vault"
    },
    "title": { "translate": "ds.advancements.open_good_vault.title" },
    "description": { "translate": "ds.advancements.open_good_vault.description" },
    "show_toast": true,
    "announce_to_chat": true,
    "frame": "goal",
    "hidden": false
  },
  "criteria": {
    "requirement": {
      "trigger": "minecraft:item_used_on_block",
      "conditions": {
        "location": [
          {
            "condition": "minecraft:location_check",
            "predicate": {
              "block": {
                "blocks": "dragonsurvival:dragon_vault_friendly"
              }
            }
          },
          {
            "condition": "minecraft:match_tool",
            "predicate": {
              "items": "dragonsurvival:good_dragon_key"
            }
          }
        ]
      }
    }
  },
  "rewards": {
    "experience": 10
  }
}